ct_redis_cache_lib/__init__.py
ct_redis_cache_lib/cache.py
flask_redis_lib-0.1.dist-info/METADATA
flask_redis_lib-0.1.dist-info/WHEEL
flask_redis_lib-0.1.dist-info/top_level.txt
flask_redis_lib-0.1.dist-info/RECORD
